Metadata-Version: 2.1
Name: keras-multilabel-embedding
Version: 0.1.1
Summary: Training of multi-label embeddings for k-shingled input sequences. for Tensorflow2/Keras
Home-page: http://github.com/ulf1/keras-multilabel-embedding
Author: Ulf Hamster
Author-email: 554c46@gmail.com
License: Apache License 2.0
Platform: UNKNOWN
Requires-Python: >=3.6
License-File: LICENSE
